sldf_splitter/__init__.py
sldf_splitter/core.py
sldf_splitter-0.1.0.dist-info/METADATA
sldf_splitter-0.1.0.dist-info/WHEEL
sldf_splitter-0.1.0.dist-info/top_level.txt
sldf_splitter-0.1.0.dist-info/RECORD
