Metadata-Version: 2.4
Name: sldf_splitter
Version: 0.1.0
Summary: Same Label, Different Features (SLDF) data partitioning tool
Author: Your Name
Requires-Python: >=3.7
Requires-Dist: pandas
Dynamic: author
Dynamic: requires-dist
Dynamic: requires-python
Dynamic: summary
